dcache_nagios_plugins/__init__.py
dcache_nagios_plugins/dcache.py
dcache_nagios_plugins/dcacheinfo.py
dcache_nagios_plugins/urlopen.py
dcache_nagios_plugins/utils.py
dcache_nagios_plugins-0.0.8.data/data/lib/nagios/plugins/check_dcache_dav_head
dcache_nagios_plugins-0.0.8.data/data/lib/nagios/plugins/check_dcache_doorslam
dcache_nagios_plugins-0.0.8.data/data/lib/nagios/plugins/check_dcache_errors
dcache_nagios_plugins-0.0.8.data/data/lib/nagios/plugins/check_dcache_linkgroup
dcache_nagios_plugins-0.0.8.data/data/lib/nagios/plugins/check_dcache_pool
dcache_nagios_plugins-0.0.8.data/data/lib/nagios/plugins/check_dcache_poolgroup
dcache_nagios_plugins-0.0.8.data/data/lib/nagios/plugins/check_dcache_restore
dcache_nagios_plugins-0.0.8.dist-info/METADATA
dcache_nagios_plugins-0.0.8.dist-info/WHEEL
dcache_nagios_plugins-0.0.8.dist-info/top_level.txt
dcache_nagios_plugins-0.0.8.dist-info/RECORD
