Metadata-Version: 2.1
Name: dcache-nagios-plugins
Version: 0.0.8
Summary: A collection of nagios plugins to monitor a dCache storage.
Home-page: https://github.com/neicnordic/dcache-nagios-plugins/
Author: Petter Urkedal, Vincent Garonne
License: Apache License, Version 2.0
Platform: UNKNOWN
Classifier: Development Status :: 5 - Production/Stable
Classifier: License :: OSI Approved :: Apache Software License
Classifier: Intended Audience :: Information Technology
Classifier: Intended Audience :: System Administrators
Classifier: Operating System :: POSIX :: Linux
Classifier: Natural Language :: English
Classifier: Programming Language :: Python
Classifier: Programming Language :: Python :: 2.7
Classifier: Environment :: No Input/Output (Daemon)
Requires-Dist: requests
